mfoutparser/__init__.py
mfoutparser/correlation.py
mfoutparser/docstring.py
mfoutparser/examples.py
mfoutparser/read.py
mfoutparser/selector.py
mfoutparser/version.py
mfoutparser/write.py
mfoutparser/examples/MFparser_demo.ipynb
mfoutparser/examples/input_data/mfout.compare
mfoutparser/examples/input_data/mfout.multifield
mfoutparser/examples/input_data/mfout.singlefield
mfoutparser/examples/output/R1_500MHz_plot.pdf
mfoutparser/examples/output/R1_500MHz_plot.png
mfoutparser/examples/output/S2_plot.pdf
mfoutparser/examples/output/S2_plot.png
mfoutparser/examples/output/mfout_compare_loop_F_dist.tsv
mfoutparser/examples/output/mfout_compare_loop_chi_square.tsv
mfoutparser/examples/output/mfout_compare_loop_correlation_matrix.tsv
mfoutparser/examples/output/mfout_compare_loop_diffusion_tensor.tsv
mfoutparser/examples/output/mfout_compare_loop_header_1.tsv
mfoutparser/examples/output/mfout_compare_loop_model_1.tsv
mfoutparser/examples/output/mfout_compare_loop_model_2.tsv
mfoutparser/examples/output/mfout_compare_loop_relaxation.tsv
mfoutparser/examples/output/mfout_compare_loop_spin_parameters.tsv
mfoutparser/examples/output/mfout_compare_loop_sse.tsv
mfoutparser/examples/output/mfout_compare_loop_title.tsv
mfoutparser/examples/output/mfout_compare_tag_chi_square.tsv
mfoutparser/examples/output/mfout_compare_tag_header.tsv
mfoutparser/examples/output/mfout_multifield_loop_diffusion_tensor.tsv
mfoutparser/examples/output/mfout_multifield_loop_header_1.tsv
mfoutparser/examples/output/mfout_multifield_loop_model_1.tsv
mfoutparser/examples/output/mfout_multifield_loop_relaxation.tsv
mfoutparser/examples/output/mfout_multifield_loop_spin_parameters.tsv
mfoutparser/examples/output/mfout_multifield_loop_sse.tsv
mfoutparser/examples/output/mfout_multifield_loop_title.tsv
mfoutparser/examples/output/mfout_multifield_tag_chi_square.tsv
mfoutparser/examples/output/mfout_multifield_tag_header.tsv
mfoutparser/examples/output/mfout_singlefield_loop_chi_square.tsv
mfoutparser-1.5.1.dist-info/METADATA
mfoutparser-1.5.1.dist-info/WHEEL
mfoutparser-1.5.1.dist-info/licenses/LICENSE.md
mfoutparser-1.5.1.dist-info/RECORD
