Metadata-Version: 2.4
Name: mfoutparser
Version: 1.5.1
Summary: Parser for STAR format mfout file generated by the program ModelFree
Project-URL: Repository, https://github.com/agpalmeriii/mfoutparser.git
Author: Michelle Gill
Author-email: Arthur Palmer <agp6@columbia.edu>
Maintainer-email: Arthur Palmer <agp6@columbia.edu>
License-File: LICENSE.md
Classifier: Development Status :: 4 - Beta
Classifier: Programming Language :: Python
Requires-Python: >=3.12
Requires-Dist: numpy
Requires-Dist: pandas
